imgprocessdio/__init__.py
imgprocessdio/processing/__init__.py
imgprocessdio/processing/combination.py
imgprocessdio/processing/transformation.py
imgprocessdio/utils/__init__.py
imgprocessdio/utils/io.py
imgprocessdio/utils/plot.py
imgprocessdio-0.0.1.dist-info/METADATA
imgprocessdio-0.0.1.dist-info/WHEEL
imgprocessdio-0.0.1.dist-info/top_level.txt
imgprocessdio-0.0.1.dist-info/RECORD
