Metadata-Version: 2.1
Name: imgprocessdio
Version: 0.0.1
Summary: Image Processing package, compare and see diffences of histograsms between images
Home-page: https://github.com/Memlith/pacote-processamento-imagem.git
Author: Caio Simonassi
Author-email: iamcaiosimonassi@gmail.com
Requires-Python: >=3.8
Requires-Dist: matplotlib
Requires-Dist: numpy
Requires-Dist: scikit-image
